VerilogBM_214/4 wheelers/VerilogBM_106_214(4wheelers).v

/*PROJECT:AUTOMATED VEHICLE PARKING ENTRY AND EXIT

//DATAFLOW VERILOG CODE FOR AUTOMATED ENTRY AND EXIT OF VEHICLES 

//CHANDRIKA.T.G-16CO214


//ABSTRACT
		
		•	Unique password will be given to each vehicle owned by the residents which works for both entry and exit.
		•	Keep the count of two wheelers and four wheelers separately at any instant of time.
		•	Separate entry for two and four wheelers.
*/
//FUNCTIONALITY AND DESCRIPTION

//There is 1 module :
//						1.module VerilogBM_214 is the main module which actually does the work for automated entry and exit
//							*inputs are buzzer press and 5 bit(decimal) password entry
//							*outputs includes whether gate is closed or open ,chance to enter the password is over or not,num of vehicles in parking slot at any given time

module VerilogBM_214(input buzzer, 				//user can enter the password only if buzzer is pressed
						input entry,			//=1 if vehicle is entering else =0
						input exit,				//=1 if vehicle is exiting else =0
						input [20:1]password,	//password entered by the user			
						input clear,			//to clear the counter to count the number of chances
						input clear_new,		//to clear the counter to count the number of chances after correct password is entered
						output reg gate_open,	//will be equal to 1 if entered password is accepted else 0
						output reg gate_closed,	//will be equal to 0 if entered password is accepted else 1 if access is denied
						output reg [1:0]count_entry,		//To count the number of times buzzer pressed by each user while entering
						output reg [1:0]count_exit,			//To count the number of times buzzer pressed by each user while exiting
						output reg [12:1]num_in_park_slot,	//Total number of vehicles in the parking slot at given point of time
						output reg [2:1]count_next_entry,	//To give count_entry+1
						output reg [2:1]count_next_exit,	//To give count_exit+1
						output reg [12:1]num_entry_next ,	//To calculate num_in_park_slot+1 while entering
						output reg [12:1]num_exit_next,		//To calculate num_in_park_slot+1 while exiting
						output reg [2:1] count_prev_entry,	//To give count_entry-1
						output reg [2:1] count_prev_exit	//To give count_exit-1
						);
	
/* ACCEPTED PASSWORDS FOR 4 WHEELERS:
	1.74321
	2.12345
	3.64777
	4.56733
	5.37565
*/


always @(buzzer or password or entry or exit or clear or clear_new)
	
	begin

	
	//To clear the both the counters(one for counting the number of chances and the other for counting num of vehicles in parking slot) 
			if(clear==1'b1)			
			begin
			count_exit=2'd0;
			count_entry=2'd0;
			num_in_park_slot=12'd0;
			end
			
			else if(clear==1'b0)
			begin
				count_entry=count_next_entry;;
			end
			
			else if(clear==1'b0)
			begin
				count_exit=count_next_exit;
			end
			
	//To calculate count_prev,count_next,num_entry_next,num_exit_next		
			count_prev_entry=count_entry;
			num_entry_next=num_in_park_slot+1;
			count_prev_exit=count_exit;
			num_exit_next=num_in_park_slot-1;
//ENTRY OF VEHICLES 
			
	//Password checking for entered password and making chance_over=0 if buzzer is pressed <3 times  else =1	
		//Password is correct means gate_open=1 ,gate_closed=0	
		if(entry==1'b1)
		begin
			
			if(count_entry==2'd3 &&(password==20'd74321|| password==20'd12345|| password==20'd64777|| password==20'd56733|| password==20'd37565) )
				count_next_entry=2'd0;
			else if(count_entry==2'd3 && (password!=20'd74321|| password!=20'd12345|| password!=20'd64777|| password!=20'd56733|| password!=20'd37565))
				count_next_entry=2'd1;
			else
				count_next_entry=count_entry+1;
			
			
			
			if(count_entry<2'd3)
			begin
				if(buzzer==1'b1 && (password==20'd74321|| password==20'd12345|| password==20'd64777|| password==20'd56733|| password==20'd37565))
				begin
					gate_open<=1'b1;
					gate_closed<=1'b0;
					num_in_park_slot=num_entry_next;
					count_entry<=2'd0;
						
				end	
				
			end
			else if(count_entry==2'd3)
				begin
					$display("\nYour Chance is over::You cannot enter the parking slot....SORRY!!:(");
				
				end
	//Password is incorrect means gate will remain closed i.e gate+closed =1 and gate_open=0			
			if(buzzer==1'b0 ||(password!=20'd74321|| password!=20'd12345|| password!=20'd64777|| password!=20'd56733|| password!=20'd37565) )
			begin
				count_entry=count_next_entry;
				gate_open=1'b0;
				gate_closed=1'b1;
				num_in_park_slot=num_in_park_slot;
				count_entry<=1'd0;
			end
		end

//EXIT OF VEHICLES 
		
		if(exit==1'b1)
		begin
	//Password checking for entered password and making chance_over=0 if buzzer is pressed <3 times  else =1	
		//Password is correct means gate_open=1 ,gate_closed=0
		
			if(count_exit==2'd3 &&(password==20'd74321|| password==20'd12345|| password==20'd64777|| password==20'd56733|| password==20'd37565) )
			count_next_exit=2'd0;
			else if(count_exit==2'd3 && (password!=20'd74321|| password!=20'd12345|| password!=20'd64777|| password!=20'd56733|| password!=20'd37565))
			count_next_exit=2'd1;
			else
			count_next_exit=count_exit+1;
			
			
			
			if(count_exit<2'd3)
			begin
				if(buzzer==1'b1 && (password==20'd74321|| password==20'd12345|| password==20'd64777|| password==20'd56733|| password==20'd37565) )
				begin
					gate_open<=1'b1;
					gate_closed<=1'b0;
					num_in_park_slot=num_exit_next;
					count_exit<=2'd0;
						
				end	
				
			end
			else if(count_exit==2'd3)
				begin
					$display("\nYour Chance is over::You cannot enter the parking slot....SORRY!!:(");
				
				end
	//Password is incorrect means gate will remain closed i.e gate_closed =1 and gate_open=0	
	
		if(buzzer==1'b0 ||(password!=20'd74321|| password!=20'd12345|| password!=20'd64777|| password!=20'd56733|| password!=20'd37565) )
			begin
				count_exit=count_next_exit;
				gate_open=1'b0;
				gate_closed=1'b1;
				num_in_park_slot=num_in_park_slot;
				count_exit=1'd0;
			end
		end
	end
endmodule

VerilogBM_214/4 wheelers/VerilogBM_106_214(4wheelers_testbench).v
/*-------------------------------------TEST BENCH------------------------------------------------*/
/*PROJECT:AUTOMATED VEHICLE PARKING ENTRY AND EXIT

//DATAFLOW VERILOG CODE FOR AUTOMATED ENTRY AND EXIT OF VEHICLES 

//CHANDRIKA.T.G-16CO214


//ABSTRACT
		
		•	Unique password will be given to each vehicle owned by the residents which works for both entry and exit.
		•	Keep the count of two wheelers and four wheelers separately at any instant of time.
		•	Separate entry for two and four wheelers.
*/
//FUNCTIONALITY
 //Following is the test bench for 2 wheelers
module Verilog_214_test;
reg buzzer; 						//user can enter the password only if buzzer is pressed
reg [20:1]password;					//password entered by the user			
reg clear;							//to clear the counter to count the number of chances
reg clear_new;						//to clear the counter to count the number of chances after correct password is entered
reg entry;							//=1 if vehicle is entering else =0
reg exit;							//=1 if vehicle is exiting else =0
wire [2:1]count_entry;				//To count the number of times buzzer pressed by each user while entering
wire [2:1]count_exit;				//To count the number of times buzzer pressed by each user while exiting
wire gate_open;						//will be equal to 1 if entered password is accepted else 0
wire gate_closed;					//will be equal to 0 if entered password is accepted else 1 if access is denied
wire [12:1]num_in_park_slot;		//Total number of vehicles in the parking slot at given point of time
wire [2:1]count_next_entry;			//To give count_entry+1
wire [2:1]count_next_exit;			//To give count_exit+1
wire [12:1]num_entry_next;			//To calculate num_in_park_slot+1 while entering
wire [12:1]num_exit_next;			//To calculate num_in_park_slot+1 while exiting
wire [2:1] count_prev_entry;		//To give count_entry-1
wire [2:1] count_prev_exit;			//To give count_exit-1
VerilogBM_214 test(buzzer,entry,exit,password,clear,clear_new,gate_open,gate_closed,count_entry,count_exit,num_in_park_slot,count_next_entry,count_next_exit,num_entry_next,num_exit_next,count_prev_entry,count_prev_exit);
initial
begin
	$dumpfile("VerilogBM_214_4w.vcd");
	$dumpvars;
end

initial begin
	buzzer=1'b0;
	clear=1'b1;
	entry=1'b1;
	exit=1'b0;
	password=0;
	#10
		entry=1'b1;
		exit=0;
		clear=1'b0;
		buzzer=1'b1;
		password=20'd74321;
	#10
		entry=1'b1;
		exit=0;
		clear=1'b0;
		buzzer=1'b1;
		password=20'd12345;
	#10
		entry=1'b1;
		exit=0;
		clear=1'b0;
		buzzer=1'b1;
		password=20'd43456;
	#10
		entry=1'b1;
		exit=0;
		clear=1'b0;
		buzzer=1'b1;
		password=20'd43678;
	#10
		exit=1'b0;
		entry=1;
		clear=1'b0;
		buzzer=1'b1;
		password=20'd46090;
	
	
	#10
		entry=1;
		exit=0;
		buzzer=1'b1;
		clear=1'b0;
		password=20'd50023;
	#10
		exit=0;
		entry=1;
		buzzer=1'b1;
		password=20'd37565;
		clear=1'b0;
	#10
		exit=1;
		entry=0;
		buzzer=1'b1;
		password=20'd74321;
		clear=1'b0;
	#10
		exit=1;
		entry=0;
		buzzer=1'b1;
		password=20'd12345;
		clear=1'b0;
		
end 
initial

$monitor("\nentry=%b\texit=%b\tBuzzer=%b\tPassword=%5d\tgate open=%b\tgate closed=%b\tnumber of vehicles in parking slot=%2d",entry,exit,buzzer,password,gate_open,gate_closed,num_in_park_slot);

endmodule

VerilogBM_214/4 wheelers/VerilogBM_106_214_4w.vcd
$date
	Tue Nov 07 19:55:27 2017
$end
$version
	Icarus Verilog
$end
$timescale
	1s
$end
$scope module Verilog_214_test $end
$var wire 12 ! num_in_park_slot [12:1] $end
$var wire 12 " num_exit_next [12:1] $end
$var wire 12 # num_entry_next [12:1] $end
$var wire 1 $ gate_open $end
$var wire 1 % gate_closed $end
$var wire 2 & count_prev_exit [2:1] $end
$var wire 2 ' count_prev_entry [2:1] $end
$var wire 2 ( count_next_exit [2:1] $end
$var wire 2 ) count_next_entry [2:1] $end
$var wire 2 * count_exit [2:1] $end
$var wire 2 + count_entry [2:1] $end
$var reg 1 , buzzer $end
$var reg 1 - clear $end
$var reg 1 . clear_new $end
$var reg 1 / entry $end
$var reg 1 0 exit $end
$var reg 20 1 password [20:1] $end
$scope module test $end
$var wire 1 , buzzer $end
$var wire 1 - clear $end
$var wire 1 . clear_new $end
$var wire 1 / entry $end
$var wire 1 0 exit $end
$var wire 20 2 password [20:1] $end
$var reg 2 3 count_entry [1:0] $end
$var reg 2 4 count_exit [1:0] $end
$var reg 2 5 count_next_entry [2:1] $end
$var reg 2 6 count_next_exit [2:1] $end
$var reg 2 7 count_prev_entry [2:1] $end
$var reg 2 8 count_prev_exit [2:1] $end
$var reg 1 % gate_closed $end
$var reg 1 $ gate_open $end
$var reg 12 9 num_entry_next [12:1] $end
$var reg 12 : num_exit_next [12:1] $end
$var reg 12 ; num_in_park_slot [12:1] $end
$upscope $end
$upscope $end
$enddefinitions $end
#0
$dumpvars
b0 ;
b111111111111 :
b1 9
b0 8
b0 7
bx 6
b1 5
b0 4
b0 3
b0 2
b0 1
00
1/
x.
1-
0,
b0 +
b0 *
b1 )
bx (
b0 '
b0 &
1%
0$
b1 #
b111111111111 "
b0 !
$end
#10
0%
1$
b1 !
b1 ;
b10 )
b10 5
b1 '
b1 7
b0 +
b0 3
b10010001001010001 1
b10010001001010001 2
1,
0-
#20
0%
1$
b10 !
b10 ;
b11 )
b11 5
b0 "
b0 :
b10 #
b10 9
b10 '
b10 7
b0 +
b0 3
b11000000111001 1
b11000000111001 2
#30
1%
0$
b1 )
b1 5
b1 "
b1 :
b11 #
b11 9
b11 '
b11 7
b0 +
b0 3
b1010100111000000 1
b1010100111000000 2
#40
b10 )
b10 5
b1 '
b1 7
b0 +
b0 3
b1010101010011110 1
b1010101010011110 2
#50
b11 )
b11 5
b10 '
b10 7
b0 +
b0 3
b1011010000001010 1
b1011010000001010 2
#60
b1 )
b1 5
b11 '
b11 7
b0 +
b0 3
b1100001101100111 1
b1100001101100111 2
#70
0%
1$
b11 !
b11 ;
b10 )
b10 5
b1 '
b1 7
b0 +
b0 3
b1001001010111101 1
b1001001010111101 2
#80
0%
1$
b0 *
b0 4
b10 !
b10 ;
b1 (
b1 6
b10 "
b10 :
b100 #
b100 9
b10 '
b10 7
b10 +
b10 3
b10010001001010001 1
b10010001001010001 2
0/
10
#90
0%
1$
b0 *
b0 4
b1 !
b1 ;
b1 "
b1 :
b11 #
b11 9
b11000000111001 1
b11000000111001 2
